websocket_executor/__init__.pyd
websocket_executor/apps.pyd
websocket_executor/consumers.pyd
websocket_executor/manager.pyd
websocket_executor/routing.pyd
websocket_executor/scripts.pyd
websocket_executor/serializers.pyd
websocket_executor/management/__init__.pyd
websocket_executor/management/commands/__init__.pyd
websocket_executor/management/commands/runserver.pyd
websocket_executor-1.0.0.30.dist-info/LICENCE
websocket_executor-1.0.0.30.dist-info/METADATA
websocket_executor-1.0.0.30.dist-info/WHEEL
websocket_executor-1.0.0.30.dist-info/top_level.txt
websocket_executor-1.0.0.30.dist-info/RECORD
